{"name":"space-armory-tycoon","className":"DataModel","filePaths":["default.project.json"],"children":[{"name":"ReplicatedStorage","className":"ReplicatedStorage","children":[{"name":"Modules","className":"Folder","filePaths":["src/ReplicatedStorage/Modules\\init.meta.json"],"children":[{"name":"AMS","className":"ModuleScript","filePaths":["src/ReplicatedStorage/Modules\\AMS\\init.lua"],"children":[{"name":"Controller","className":"ModuleScript","filePaths":["src/ReplicatedStorage/Modules\\AMS\\Controller.lua"]},{"name":"Scripts","className":"Folder","filePaths":["src/ReplicatedStorage/Modules\\AMS\\Scripts\\init.meta.json"],"children":[{"name":"Client","className":"Script","filePaths":["src/ReplicatedStorage/Modules\\AMS\\Scripts\\Client.client.lua","src/ReplicatedStorage/Modules\\AMS\\Scripts\\Client.meta.json"]},{"name":"Server","className":"Script","filePaths":["src/ReplicatedStorage/Modules\\AMS\\Scripts\\Server.server.lua"]},{"name":"StarterCharacter","className":"Script","filePaths":["src/ReplicatedStorage/Modules\\AMS\\Scripts\\StarterCharacter.client.lua","src/ReplicatedStorage/Modules\\AMS\\Scripts\\StarterCharacter.meta.json"]}]},{"name":"Setup","className":"ModuleScript","filePaths":["src/ReplicatedStorage/Modules\\AMS\\Setup.lua"]}]},{"name":"Backpack","className":"ModuleScript","filePaths":["src/ReplicatedStorage/Modules\\Backpack\\init.lua"],"children":[{"name":"Scripts","className":"Folder","filePaths":["src/ReplicatedStorage/Modules\\Backpack\\Scripts\\init.meta.json"],"children":[{"name":"Client","className":"Script","filePaths":["src/ReplicatedStorage/Modules\\Backpack\\Scripts\\Client.client.lua","src/ReplicatedStorage/Modules\\Backpack\\Scripts\\Client.meta.json"]},{"name":"StarterCharacter","className":"Script","filePaths":["src/ReplicatedStorage/Modules\\Backpack\\Scripts\\StarterCharacter.client.lua","src/ReplicatedStorage/Modules\\Backpack\\Scripts\\StarterCharacter.meta.json"]}]},{"name":"_Base","className":"ModuleScript","filePaths":["src/ReplicatedStorage/Modules\\Backpack\\_Base.lua"]}]},{"name":"Badges","className":"ModuleScript","filePaths":["src/ReplicatedStorage/Modules\\Badges.lua"]},{"name":"Casting","className":"ModuleScript","filePaths":["src/ReplicatedStorage/Modules\\Casting\\init.lua"],"children":[{"name":"ClientCaster","className":"ModuleScript","filePaths":["src/ReplicatedStorage/Modules\\Casting\\ClientCaster\\init.lua"],"children":[{"name":"FastCastRedux","className":"ModuleScript","filePaths":["src/ReplicatedStorage/Modules\\Casting\\ClientCaster\\FastCastRedux\\init.lua"],"children":[{"name":"ActiveCast","className":"ModuleScript","filePaths":["src/ReplicatedStorage/Modules\\Casting\\ClientCaster\\FastCastRedux\\ActiveCast.lua"]},{"name":"PartCache","className":"ModuleScript","filePaths":["src/ReplicatedStorage/Modules\\Casting\\ClientCaster\\FastCastRedux\\PartCache\\init.lua"],"children":[{"name":"Table","className":"ModuleScript","filePaths":["src/ReplicatedStorage/Modules\\Casting\\ClientCaster\\FastCastRedux\\PartCache\\Table.lua"]}]},{"name":"Signal","className":"ModuleScript","filePaths":["src/ReplicatedStorage/Modules\\Casting\\ClientCaster\\FastCastRedux\\Signal.lua"]},{"name":"Table","className":"ModuleScript","filePaths":["src/ReplicatedStorage/Modules\\Casting\\ClientCaster\\FastCastRedux\\Table.lua"]},{"name":"TypeDefinitions","className":"ModuleScript","filePaths":["src/ReplicatedStorage/Modules\\Casting\\ClientCaster\\FastCastRedux\\TypeDefinitions.lua"]},{"name":"TypeMarshaller","className":"ModuleScript","filePaths":["src/ReplicatedStorage/Modules\\Casting\\ClientCaster\\FastCastRedux\\TypeMarshaller.lua"]}]}]},{"name":"Results","className":"ModuleScript","filePaths":["src/ReplicatedStorage/Modules\\Casting\\Results\\init.lua"],"children":[{"name":"Actions","className":"ModuleScript","filePaths":["src/ReplicatedStorage/Modules\\Casting\\Results\\Actions.lua"]},{"name":"Effects","className":"ModuleScript","filePaths":["src/ReplicatedStorage/Modules\\Casting\\Results\\Effects\\init.lua"],"children":[{"name":"BoatTween","className":"ModuleScript","filePaths":["src/ReplicatedStorage/Modules\\Casting\\Results\\Effects\\BoatTween\\init.lua"],"children":[{"name":"Bezier","className":"ModuleScript","filePaths":["src/ReplicatedStorage/Modules\\Casting\\Results\\Effects\\BoatTween\\Bezier.lua"]},{"name":"Lerps","className":"ModuleScript","filePaths":["src/ReplicatedStorage/Modules\\Casting\\Results\\Effects\\BoatTween\\Lerps.lua"]},{"name":"TweenFunctions","className":"ModuleScript","filePaths":["src/ReplicatedStorage/Modules\\Casting\\Results\\Effects\\BoatTween\\TweenFunctions.lua"]}]}]}]},{"name":"ServerCaster","className":"ModuleScript","filePaths":["src/ReplicatedStorage/Modules\\Casting\\ServerCaster.lua"]},{"name":"TypeDefinitions","className":"ModuleScript","filePaths":["src/ReplicatedStorage/Modules\\Casting\\TypeDefinitions.lua"]}]},{"name":"Damage","className":"ModuleScript","filePaths":["src/ReplicatedStorage/Modules\\Damage\\init.lua"],"children":[{"name":"Actions","className":"ModuleScript","filePaths":["src/ReplicatedStorage/Modules\\Damage\\Actions.lua"]},{"name":"Damage","className":"ModuleScript","filePaths":["src/ReplicatedStorage/Modules\\Damage\\Damage.lua"]},{"name":"Scripts","className":"Folder","filePaths":["src/ReplicatedStorage/Modules\\Damage\\Scripts\\init.meta.json"],"children":[{"name":"Client","className":"Script","filePaths":["src/ReplicatedStorage/Modules\\Damage\\Scripts\\Client.client.lua"]},{"name":"Server","className":"Script","filePaths":["src/ReplicatedStorage/Modules\\Damage\\Scripts\\Server.server.lua"]}]},{"name":"Setup","className":"ModuleScript","filePaths":["src/ReplicatedStorage/Modules\\Damage\\Setup.lua"]},{"name":"TypeDefinitions","className":"ModuleScript","filePaths":["src/ReplicatedStorage/Modules\\Damage\\TypeDefinitions.lua"]}]},{"name":"Explosions","className":"ModuleScript","filePaths":["src/ReplicatedStorage/Modules\\Explosions\\init.lua"],"children":[{"name":"Explosion","className":"ModuleScript","filePaths":["src/ReplicatedStorage/Modules\\Explosions\\Explosion.lua"]},{"name":"TypeDefinitions","className":"ModuleScript","filePaths":["src/ReplicatedStorage/Modules\\Explosions\\TypeDefinitions.lua"]}]},{"name":"Game","className":"ModuleScript","filePaths":["src/ReplicatedStorage/Modules\\Game\\init.lua"],"children":[{"name":"Tools","className":"ModuleScript","filePaths":["src/ReplicatedStorage/Modules\\Game\\Tools\\init.lua"],"children":[{"name":"Cloned","className":"Folder","filePaths":["src/ReplicatedStorage/Modules\\Game\\Tools\\Cloned\\init.meta.json"],"children":[{"name":"GunSpawner","className":"Script","filePaths":["src/ReplicatedStorage/Modules\\Game\\Tools\\Cloned\\GunSpawner.client.lua"]}]},{"name":"Manager","className":"ModuleScript","filePaths":["src/ReplicatedStorage/Modules\\Game\\Tools\\Manager.lua"]},{"name":"Scripts","className":"Folder","filePaths":["src/ReplicatedStorage/Modules\\Game\\Tools\\Scripts\\init.meta.json"],"children":[{"name":"Server","className":"Script","filePaths":["src/ReplicatedStorage/Modules\\Game\\Tools\\Scripts\\Server.server.lua","src/ReplicatedStorage/Modules\\Game\\Tools\\Scripts\\Server.meta.json"]}]},{"name":"Utils","className":"ModuleScript","filePaths":["src/ReplicatedStorage/Modules\\Game\\Tools\\Utils.lua"]}]},{"name":"Tycoons","className":"ModuleScript","filePaths":["src/ReplicatedStorage/Modules\\Game\\Tycoons\\init.lua"],"children":[{"name":"Manager","className":"ModuleScript","filePaths":["src/ReplicatedStorage/Modules\\Game\\Tycoons\\Manager.lua"]},{"name":"Utils","className":"ModuleScript","filePaths":["src/ReplicatedStorage/Modules\\Game\\Tycoons\\Utils.lua"]}]},{"name":"Vehicles","className":"ModuleScript","filePaths":["src/ReplicatedStorage/Modules\\Game\\Vehicles\\init.lua"],"children":[{"name":"Cloned","className":"Folder","filePaths":["src/ReplicatedStorage/Modules\\Game\\Vehicles\\Cloned\\init.meta.json"],"children":[{"name":"VehicleSpawner","className":"Script","filePaths":["src/ReplicatedStorage/Modules\\Game\\Vehicles\\Cloned\\VehicleSpawner.client.lua"]}]},{"name":"Manager","className":"ModuleScript","filePaths":["src/ReplicatedStorage/Modules\\Game\\Vehicles\\Manager.lua"]},{"name":"Scripts","className":"Folder","filePaths":["src/ReplicatedStorage/Modules\\Game\\Vehicles\\Scripts\\init.meta.json"],"children":[{"name":"Server","className":"Script","filePaths":["src/ReplicatedStorage/Modules\\Game\\Vehicles\\Scripts\\Server.server.lua","src/ReplicatedStorage/Modules\\Game\\Vehicles\\Scripts\\Server.meta.json"]}]},{"name":"Utils","className":"ModuleScript","filePaths":["src/ReplicatedStorage/Modules\\Game\\Vehicles\\Utils.lua"]}]}]},{"name":"Guns","className":"ModuleScript","filePaths":["src/ReplicatedStorage/Modules\\Guns\\init.lua"],"children":[{"name":"ClientGun","className":"ModuleScript","filePaths":["src/ReplicatedStorage/Modules\\Guns\\ClientGun.lua"]},{"name":"Cloned","className":"Folder","filePaths":["src/ReplicatedStorage/Modules\\Guns\\Cloned\\init.meta.json"],"children":[{"name":"Client","className":"Script","filePaths":["src/ReplicatedStorage/Modules\\Guns\\Cloned\\Client.client.lua"]},{"name":"Server","className":"Script","filePaths":["src/ReplicatedStorage/Modules\\Guns\\Cloned\\Server.server.lua"]}]},{"name":"Scripts","className":"Folder","filePaths":["src/ReplicatedStorage/Modules\\Guns\\Scripts\\init.meta.json"],"children":[{"name":"Client","className":"Script","filePaths":["src/ReplicatedStorage/Modules\\Guns\\Scripts\\Client.client.lua"]}]},{"name":"ServerGun","className":"ModuleScript","filePaths":["src/ReplicatedStorage/Modules\\Guns\\ServerGun.lua"]},{"name":"Utils","className":"ModuleScript","filePaths":["src/ReplicatedStorage/Modules\\Guns\\Utils.lua"]}]},{"name":"Leaderboard","className":"ModuleScript","filePaths":["src/ReplicatedStorage/Modules\\Leaderboard.lua"]},{"name":"Mega","className":"ModuleScript","filePaths":["src/ReplicatedStorage/Modules\\Mega\\init.meta.json","src/ReplicatedStorage/Modules\\Mega\\init.lua"],"children":[{"name":"Boot","className":"ModuleScript","filePaths":["src/ReplicatedStorage/Modules\\Mega\\Boot.lua"]},{"name":"Command","className":"ModuleScript","filePaths":["src/ReplicatedStorage/Modules\\Mega\\Command\\init.lua"],"children":[{"name":"Command","className":"ModuleScript","filePaths":["src/ReplicatedStorage/Modules\\Mega\\Command\\Command.lua"]},{"name":"Listener","className":"ModuleScript","filePaths":["src/ReplicatedStorage/Modules\\Mega\\Command\\Listener.lua"]},{"name":"Utils","className":"ModuleScript","filePaths":["src/ReplicatedStorage/Modules\\Mega\\Command\\Utils.lua"]}]},{"name":"Data","className":"ModuleScript","filePaths":["src/ReplicatedStorage/Modules\\Mega\\Data\\init.lua"],"children":[{"name":"BetterStore","className":"ModuleScript","filePaths":["src/ReplicatedStorage/Modules\\Mega\\Data\\BetterStore.lua"]},{"name":"InstanceAPI","className":"ModuleScript","filePaths":["src/ReplicatedStorage/Modules\\Mega\\Data\\InstanceAPI.lua"]},{"name":"LiveConfig","className":"ModuleScript","filePaths":["src/ReplicatedStorage/Modules\\Mega\\Data\\LiveConfig\\init.lua"],"children":[{"name":"_Test","className":"ModuleScript","filePaths":["src/ReplicatedStorage/Modules\\Mega\\Data\\LiveConfig\\_Test.lua"]}]},{"name":"PSCache","className":"ModuleScript","filePaths":["src/ReplicatedStorage/Modules\\Mega\\Data\\PSCache.lua"]},{"name":"PlayerSettings","className":"ModuleScript","filePaths":["src/ReplicatedStorage/Modules\\Mega\\Data\\PlayerSettings.lua","src/ReplicatedStorage/Modules\\Mega\\Data\\PlayerSettings.meta.json"]}]},{"name":"DataStructures","className":"ModuleScript","filePaths":["src/ReplicatedStorage/Modules\\Mega\\DataStructures\\init.lua"],"children":[{"name":"Set","className":"ModuleScript","filePaths":["src/ReplicatedStorage/Modules\\Mega\\DataStructures\\Set.lua"]},{"name":"Table","className":"ModuleScript","filePaths":["src/ReplicatedStorage/Modules\\Mega\\DataStructures\\Table.lua"]},{"name":"_Test","className":"ModuleScript","filePaths":["src/ReplicatedStorage/Modules\\Mega\\DataStructures\\_Test.lua"]}]},{"name":"Instances","className":"ModuleScript","filePaths":["src/ReplicatedStorage/Modules\\Mega\\Instances\\init.lua"],"children":[{"name":"Modify","className":"ModuleScript","filePaths":["src/ReplicatedStorage/Modules\\Mega\\Instances\\Modify.lua"]},{"name":"Physics","className":"ModuleScript","filePaths":["src/ReplicatedStorage/Modules\\Mega\\Instances\\Physics.lua"]},{"name":"Resolve","className":"ModuleScript","filePaths":["src/ReplicatedStorage/Modules\\Mega\\Instances\\Resolve.lua"]},{"name":"Search","className":"ModuleScript","filePaths":["src/ReplicatedStorage/Modules\\Mega\\Instances\\Search.lua"]}]},{"name":"Interface","className":"ModuleScript","filePaths":["src/ReplicatedStorage/Modules\\Mega\\Interface\\init.lua"],"children":[{"name":"Context","className":"ModuleScript","filePaths":["src/ReplicatedStorage/Modules\\Mega\\Interface\\Context\\init.lua"],"children":[{"name":"_Effects","className":"ModuleScript","filePaths":["src/ReplicatedStorage/Modules\\Mega\\Interface\\Context\\_Effects.lua"]}]},{"name":"Loader","className":"ModuleScript","filePaths":["src/ReplicatedStorage/Modules\\Mega\\Interface\\Loader.lua"]},{"name":"Notification","className":"ModuleScript","filePaths":["src/ReplicatedStorage/Modules\\Mega\\Interface\\Notification.lua"]},{"name":"Scripts","className":"Folder","filePaths":["src/ReplicatedStorage/Modules\\Mega\\Interface\\Scripts\\init.meta.json"],"children":[{"name":"Server","className":"Script","filePaths":["src/ReplicatedStorage/Modules\\Mega\\Interface\\Scripts\\Server.server.lua"]}]},{"name":"Utils","className":"ModuleScript","filePaths":["src/ReplicatedStorage/Modules\\Mega\\Interface\\Utils.lua"]}]},{"name":"Logging","className":"ModuleScript","filePaths":["src/ReplicatedStorage/Modules\\Mega\\Logging\\init.lua"],"children":[{"name":"_Test","className":"ModuleScript","filePaths":["src/ReplicatedStorage/Modules\\Mega\\Logging\\_Test.lua"]}]},{"name":"Promise","className":"ModuleScript","filePaths":["src/ReplicatedStorage/Modules\\Mega\\Promise\\init.lua"],"children":[{"name":"_Test","className":"ModuleScript","filePaths":["src/ReplicatedStorage/Modules\\Mega\\Promise\\_Test.lua"]}]},{"name":"Replication","className":"ModuleScript","filePaths":["src/ReplicatedStorage/Modules\\Mega\\Replication\\init.lua"],"children":[{"name":"Decorators","className":"ModuleScript","filePaths":["src/ReplicatedStorage/Modules\\Mega\\Replication\\Decorators.lua","src/ReplicatedStorage/Modules\\Mega\\Replication\\Decorators.meta.json"]},{"name":"Server","className":"ModuleScript","filePaths":["src/ReplicatedStorage/Modules\\Mega\\Replication\\Server\\init.lua"],"children":[{"name":"_Test","className":"ModuleScript","filePaths":["src/ReplicatedStorage/Modules\\Mega\\Replication\\Server\\_Test.lua"]}]}]},{"name":"Scripts","className":"Folder","filePaths":["src/ReplicatedStorage/Modules\\Mega\\Scripts\\init.meta.json"],"children":[{"name":"_BootClient","className":"Script","filePaths":["src/ReplicatedStorage/Modules\\Mega\\Scripts\\_BootClient.client.lua"]},{"name":"_BootServer","className":"Script","filePaths":["src/ReplicatedStorage/Modules\\Mega\\Scripts\\_BootServer.server.lua"]}]},{"name":"Testing","className":"ModuleScript","filePaths":["src/ReplicatedStorage/Modules\\Mega\\Testing.lua"]},{"name":"Tutorial","className":"ModuleScript","filePaths":["src/ReplicatedStorage/Modules\\Mega\\Tutorial\\init.lua"],"children":[{"name":"Beam","className":"ModuleScript","filePaths":["src/ReplicatedStorage/Modules\\Mega\\Tutorial\\Beam.lua"]},{"name":"Notification","className":"ModuleScript","filePaths":["src/ReplicatedStorage/Modules\\Mega\\Tutorial\\Notification.lua"]},{"name":"Popup","className":"ModuleScript","filePaths":["src/ReplicatedStorage/Modules\\Mega\\Tutorial\\Popup.lua"]}]},{"name":"Utils","className":"ModuleScript","filePaths":["src/ReplicatedStorage/Modules\\Mega\\Utils\\init.lua"],"children":[{"name":"AnimManager","className":"ModuleScript","filePaths":["src/ReplicatedStorage/Modules\\Mega\\Utils\\AnimManager.lua"]},{"name":"ConnManager","className":"ModuleScript","filePaths":["src/ReplicatedStorage/Modules\\Mega\\Utils\\ConnManager.lua"]},{"name":"EffectsManager","className":"ModuleScript","filePaths":["src/ReplicatedStorage/Modules\\Mega\\Utils\\EffectsManager.lua"]},{"name":"InstanceCache","className":"ModuleScript","filePaths":["src/ReplicatedStorage/Modules\\Mega\\Utils\\InstanceCache.lua"]},{"name":"Math","className":"ModuleScript","filePaths":["src/ReplicatedStorage/Modules\\Mega\\Utils\\Math.lua"]},{"name":"Misc","className":"ModuleScript","filePaths":["src/ReplicatedStorage/Modules\\Mega\\Utils\\Misc.lua"]},{"name":"Player","className":"ModuleScript","filePaths":["src/ReplicatedStorage/Modules\\Mega\\Utils\\Player.lua"]},{"name":"Signal","className":"ModuleScript","filePaths":["src/ReplicatedStorage/Modules\\Mega\\Utils\\Signal\\init.lua"],"children":[{"name":"_Test","className":"ModuleScript","filePaths":["src/ReplicatedStorage/Modules\\Mega\\Utils\\Signal\\_Test.lua"]}]},{"name":"Space","className":"ModuleScript","filePaths":["src/ReplicatedStorage/Modules\\Mega\\Utils\\Space.lua"]},{"name":"Timer","className":"ModuleScript","filePaths":["src/ReplicatedStorage/Modules\\Mega\\Utils\\Timer\\init.lua"],"children":[{"name":"_Test","className":"ModuleScript","filePaths":["src/ReplicatedStorage/Modules\\Mega\\Utils\\Timer\\_Test.lua"]}]}]}]},{"name":"Monetization","className":"ModuleScript","filePaths":["src/ReplicatedStorage/Modules\\Monetization\\init.lua"],"children":[{"name":"Cash","className":"ModuleScript","filePaths":["src/ReplicatedStorage/Modules\\Monetization\\Cash.lua"]},{"name":"CashBoosts","className":"ModuleScript","filePaths":["src/ReplicatedStorage/Modules\\Monetization\\CashBoosts\\init.lua"],"children":[{"name":"CashBoost","className":"ModuleScript","filePaths":["src/ReplicatedStorage/Modules\\Monetization\\CashBoosts\\CashBoost.lua"]},{"name":"Manager","className":"ModuleScript","filePaths":["src/ReplicatedStorage/Modules\\Monetization\\CashBoosts\\Manager.lua"]}]},{"name":"Chests","className":"ModuleScript","filePaths":["src/ReplicatedStorage/Modules\\Monetization\\Chests.lua"]},{"name":"Cloned","className":"Folder","filePaths":["src/ReplicatedStorage/Modules\\Monetization\\Cloned\\init.meta.json"],"children":[{"name":"WorldPass","className":"Script","filePaths":["src/ReplicatedStorage/Modules\\Monetization\\Cloned\\WorldPass.server.lua"]}]},{"name":"DailySpinner","className":"ModuleScript","filePaths":["src/ReplicatedStorage/Modules\\Monetization\\DailySpinner.lua"]},{"name":"Scripts","className":"Folder","filePaths":["src/ReplicatedStorage/Modules\\Monetization\\Scripts\\init.meta.json"],"children":[{"name":"Server","className":"Script","filePaths":["src/ReplicatedStorage/Modules\\Monetization\\Scripts\\Server.server.lua"]}]},{"name":"Utils","className":"ModuleScript","filePaths":["src/ReplicatedStorage/Modules\\Monetization\\Utils.lua"]}]},{"name":"Music","className":"ModuleScript","filePaths":["src/ReplicatedStorage/Modules\\Music.lua"]},{"name":"Objects","className":"ModuleScript","filePaths":["src/ReplicatedStorage/Modules\\Objects\\init.lua"],"children":[{"name":"Doors","className":"ModuleScript","filePaths":["src/ReplicatedStorage/Modules\\Objects\\Doors\\init.lua"],"children":[{"name":"Door","className":"ModuleScript","filePaths":["src/ReplicatedStorage/Modules\\Objects\\Doors\\Door.lua"]},{"name":"LaserDoor","className":"ModuleScript","filePaths":["src/ReplicatedStorage/Modules\\Objects\\Doors\\LaserDoor\\init.lua"],"children":[{"name":"Cloned","className":"Folder","filePaths":["src/ReplicatedStorage/Modules\\Objects\\Doors\\LaserDoor\\Cloned\\init.meta.json"],"children":[{"name":"LaserGate","className":"Script","filePaths":["src/ReplicatedStorage/Modules\\Objects\\Doors\\LaserDoor\\Cloned\\LaserGate.server.lua"]}]},{"name":"Scripts","className":"Folder","filePaths":["src/ReplicatedStorage/Modules\\Objects\\Doors\\LaserDoor\\Scripts\\init.meta.json"],"children":[{"name":"Server","className":"Script","filePaths":["src/ReplicatedStorage/Modules\\Objects\\Doors\\LaserDoor\\Scripts\\Server.server.lua"]}]}]}]},{"name":"LootBag","className":"ModuleScript","filePaths":["src/ReplicatedStorage/Modules\\Objects\\LootBag.lua"]},{"name":"RepairKit","className":"ModuleScript","filePaths":["src/ReplicatedStorage/Modules\\Objects\\RepairKit\\init.lua"],"children":[{"name":"Cloned","className":"Folder","filePaths":["src/ReplicatedStorage/Modules\\Objects\\RepairKit\\Cloned\\init.meta.json"],"children":[{"name":"Client","className":"Script","filePaths":["src/ReplicatedStorage/Modules\\Objects\\RepairKit\\Cloned\\Client.client.lua"]},{"name":"Server","className":"Script","filePaths":["src/ReplicatedStorage/Modules\\Objects\\RepairKit\\Cloned\\Server.server.lua"]}]},{"name":"Scripts","className":"Folder","filePaths":["src/ReplicatedStorage/Modules\\Objects\\RepairKit\\Scripts\\init.meta.json"],"children":[{"name":"Server","className":"Script","filePaths":["src/ReplicatedStorage/Modules\\Objects\\RepairKit\\Scripts\\Server.server.lua"]}]}]},{"name":"Target","className":"ModuleScript","filePaths":["src/ReplicatedStorage/Modules\\Objects\\Target\\init.lua"],"children":[{"name":"Cloned","className":"Folder","filePaths":["src/ReplicatedStorage/Modules\\Objects\\Target\\Cloned\\init.meta.json"],"children":[{"name":"Server","className":"Script","filePaths":["src/ReplicatedStorage/Modules\\Objects\\Target\\Cloned\\Server.server.lua"]}]},{"name":"Scripts","className":"Folder","filePaths":["src/ReplicatedStorage/Modules\\Objects\\Target\\Scripts\\init.meta.json"],"children":[{"name":"Server","className":"Script","filePaths":["src/ReplicatedStorage/Modules\\Objects\\Target\\Scripts\\Server.server.lua"]}]}]},{"name":"TycoonShield","className":"ModuleScript","filePaths":["src/ReplicatedStorage/Modules\\Objects\\TycoonShield\\init.lua"],"children":[{"name":"Cloned","className":"Folder","filePaths":["src/ReplicatedStorage/Modules\\Objects\\TycoonShield\\Cloned\\init.meta.json"],"children":[{"name":"TycoonShield","className":"Script","filePaths":["src/ReplicatedStorage/Modules\\Objects\\TycoonShield\\Cloned\\TycoonShield.server.lua"]}]},{"name":"Scripts","className":"Folder","filePaths":["src/ReplicatedStorage/Modules\\Objects\\TycoonShield\\Scripts\\init.meta.json"],"children":[{"name":"Server","className":"Script","filePaths":["src/ReplicatedStorage/Modules\\Objects\\TycoonShield\\Scripts\\Server.server.lua"]}]}]},{"name":"TycoonVault","className":"ModuleScript","filePaths":["src/ReplicatedStorage/Modules\\Objects\\TycoonVault.lua"]}]},{"name":"Parties","className":"ModuleScript","filePaths":["src/ReplicatedStorage/Modules\\Parties\\init.meta.json","src/ReplicatedStorage/Modules\\Parties\\init.lua"],"children":[{"name":"Manager","className":"ModuleScript","filePaths":["src/ReplicatedStorage/Modules\\Parties\\Manager\\init.lua"],"children":[{"name":"_Base","className":"ModuleScript","filePaths":["src/ReplicatedStorage/Modules\\Parties\\Manager\\_Base.lua"]}]},{"name":"Party","className":"ModuleScript","filePaths":["src/ReplicatedStorage/Modules\\Parties\\Party.lua"]},{"name":"Scripts","className":"Folder","filePaths":["src/ReplicatedStorage/Modules\\Parties\\Scripts\\init.meta.json"],"children":[{"name":"Server","className":"Script","filePaths":["src/ReplicatedStorage/Modules\\Parties\\Scripts\\Server.server.lua"]}]},{"name":"Utils","className":"ModuleScript","filePaths":["src/ReplicatedStorage/Modules\\Parties\\Utils.lua"]}]},{"name":"PlayerData","className":"ModuleScript","filePaths":["src/ReplicatedStorage/Modules\\PlayerData.lua"]},{"name":"PointCapture","className":"ModuleScript","filePaths":["src/ReplicatedStorage/Modules\\PointCapture.lua"]},{"name":"Prizes","className":"ModuleScript","filePaths":["src/ReplicatedStorage/Modules\\Prizes\\init.lua"],"children":[{"name":"Codes","className":"ModuleScript","filePaths":["src/ReplicatedStorage/Modules\\Prizes\\Codes.lua"]},{"name":"Freebies","className":"ModuleScript","filePaths":["src/ReplicatedStorage/Modules\\Prizes\\Freebies.lua"]},{"name":"Utils","className":"ModuleScript","filePaths":["src/ReplicatedStorage/Modules\\Prizes\\Utils.lua"]}]},{"name":"Rejoin","className":"ModuleScript","filePaths":["src/ReplicatedStorage/Modules\\Rejoin\\init.meta.json","src/ReplicatedStorage/Modules\\Rejoin\\init.lua"],"children":[{"name":"Scripts","className":"Folder","filePaths":["src/ReplicatedStorage/Modules\\Rejoin\\Scripts\\init.meta.json"],"children":[{"name":"Client","className":"Script","filePaths":["src/ReplicatedStorage/Modules\\Rejoin\\Scripts\\Client.client.lua"]},{"name":"Server","className":"Script","filePaths":["src/ReplicatedStorage/Modules\\Rejoin\\Scripts\\Server.server.lua"]}]}]},{"name":"RemoteConfig","className":"ModuleScript","filePaths":["src/ReplicatedStorage/Modules\\RemoteConfig\\init.lua"],"children":[{"name":"Studio","className":"Folder","filePaths":["src/ReplicatedStorage/Modules\\RemoteConfig\\Studio\\init.meta.json"],"children":[{"name":"Update","className":"ModuleScript","filePaths":["src/ReplicatedStorage/Modules\\RemoteConfig\\Studio\\Update.lua"]}]}]},{"name":"Sentries","className":"ModuleScript","filePaths":["src/ReplicatedStorage/Modules\\Sentries\\init.meta.json","src/ReplicatedStorage/Modules\\Sentries\\init.lua"],"children":[{"name":"Cloned","className":"Folder","filePaths":["src/ReplicatedStorage/Modules\\Sentries\\Cloned\\init.meta.json"],"children":[{"name":"ClientSentry","className":"Script","filePaths":["src/ReplicatedStorage/Modules\\Sentries\\Cloned\\ClientSentry.client.lua"]},{"name":"ServerSentry","className":"Script","filePaths":["src/ReplicatedStorage/Modules\\Sentries\\Cloned\\ServerSentry.server.lua"]}]},{"name":"Scripts","className":"Folder","filePaths":["src/ReplicatedStorage/Modules\\Sentries\\Scripts\\init.meta.json"],"children":[{"name":"Server","className":"Script","filePaths":["src/ReplicatedStorage/Modules\\Sentries\\Scripts\\Server.server.lua"]}]},{"name":"Sentry","className":"ModuleScript","filePaths":["src/ReplicatedStorage/Modules\\Sentries\\Sentry.lua"]}]},{"name":"Strafer","className":"ModuleScript","filePaths":["src/ReplicatedStorage/Modules\\Strafer.lua","src/ReplicatedStorage/Modules\\Strafer.meta.json"]},{"name":"Studio","className":"ModuleScript","filePaths":["src/ReplicatedStorage/Modules\\Studio\\init.lua"],"children":[{"name":"UpdateFriction","className":"ModuleScript","filePaths":["src/ReplicatedStorage/Modules\\Studio\\UpdateFriction.lua"]}]},{"name":"Turrets","className":"ModuleScript","filePaths":["src/ReplicatedStorage/Modules\\Turrets\\init.lua"],"children":[{"name":"ClientTurret","className":"ModuleScript","filePaths":["src/ReplicatedStorage/Modules\\Turrets\\ClientTurret.lua"]},{"name":"Cloned","className":"Folder","filePaths":["src/ReplicatedStorage/Modules\\Turrets\\Cloned\\init.meta.json"],"children":[{"name":"TurretClient","className":"Script","filePaths":["src/ReplicatedStorage/Modules\\Turrets\\Cloned\\TurretClient.client.lua"]},{"name":"TurretServer","className":"Script","filePaths":["src/ReplicatedStorage/Modules\\Turrets\\Cloned\\TurretServer.server.lua"]}]},{"name":"Scripts","className":"Folder","filePaths":["src/ReplicatedStorage/Modules\\Turrets\\Scripts\\init.meta.json"],"children":[{"name":"Client","className":"Script","filePaths":["src/ReplicatedStorage/Modules\\Turrets\\Scripts\\Client.client.lua"]}]},{"name":"ServerTurret","className":"ModuleScript","filePaths":["src/ReplicatedStorage/Modules\\Turrets\\ServerTurret.lua"]},{"name":"Utils","className":"ModuleScript","filePaths":["src/ReplicatedStorage/Modules\\Turrets\\Utils.lua"]}]},{"name":"Tycoons","className":"ModuleScript","filePaths":["src/ReplicatedStorage/Modules\\Tycoons\\init.lua"],"children":[{"name":"Scripts","className":"Folder","filePaths":["src/ReplicatedStorage/Modules\\Tycoons\\Scripts\\init.meta.json"],"children":[{"name":"Client","className":"Script","filePaths":["src/ReplicatedStorage/Modules\\Tycoons\\Scripts\\Client.client.lua","src/ReplicatedStorage/Modules\\Tycoons\\Scripts\\Client.meta.json"]}]},{"name":"System","className":"ModuleScript","filePaths":["src/ReplicatedStorage/Modules\\Tycoons\\System.lua"]},{"name":"Tycoon","className":"ModuleScript","filePaths":["src/ReplicatedStorage/Modules\\Tycoons\\Tycoon.lua"]},{"name":"Utils","className":"ModuleScript","filePaths":["src/ReplicatedStorage/Modules\\Tycoons\\Utils.lua"]}]},{"name":"Vehicles","className":"ModuleScript","filePaths":["src/ReplicatedStorage/Modules\\Vehicles\\init.lua"],"children":[{"name":"Car","className":"ModuleScript","filePaths":["src/ReplicatedStorage/Modules\\Vehicles\\Car.lua"]},{"name":"Helicopter","className":"ModuleScript","filePaths":["src/ReplicatedStorage/Modules\\Vehicles\\Helicopter.lua"]},{"name":"Scripts","className":"Folder","filePaths":["src/ReplicatedStorage/Modules\\Vehicles\\Scripts\\init.meta.json"],"children":[{"name":"Client","className":"Script","filePaths":["src/ReplicatedStorage/Modules\\Vehicles\\Scripts\\Client.client.lua"]},{"name":"Server","className":"Script","filePaths":["src/ReplicatedStorage/Modules\\Vehicles\\Scripts\\Server.server.lua"]}]},{"name":"Setup","className":"ModuleScript","filePaths":["src/ReplicatedStorage/Modules\\Vehicles\\Setup.lua"]},{"name":"Utils","className":"ModuleScript","filePaths":["src/ReplicatedStorage/Modules\\Vehicles\\Utils.lua"]},{"name":"Vehicle","className":"ModuleScript","filePaths":["src/ReplicatedStorage/Modules\\Vehicles\\Vehicle.lua"]}]}]}]},{"name":"ServerScriptService","className":"ServerScriptService","children":[{"name":"Admin","className":"Script","filePaths":["src/ServerScriptService\\Admin.server.lua"]},{"name":"Billbaords","className":"Script","filePaths":["src/ServerScriptService\\Billbaords\\init.server.lua"],"children":[{"name":"Boost","className":"Script","filePaths":["src/ServerScriptService\\Billbaords\\Boost.server.lua"]},{"name":"Cash","className":"Script","filePaths":["src/ServerScriptService\\Billbaords\\Cash.server.lua"]},{"name":"Chest","className":"Script","filePaths":["src/ServerScriptService\\Billbaords\\Chest.server.lua"]},{"name":"Freebie","className":"Script","filePaths":["src/ServerScriptService\\Billbaords\\Freebie.server.lua"]},{"name":"Pass","className":"Script","filePaths":["src/ServerScriptService\\Billbaords\\Pass.server.lua"]}]},{"name":"Clock","className":"Script","filePaths":["src/ServerScriptService\\Clock.server.lua"]},{"name":"Collisions","className":"Script","filePaths":["src/ServerScriptService\\Collisions.server.lua"]},{"name":"ExperienceNotifications","className":"Script","filePaths":["src/ServerScriptService\\ExperienceNotifications.server.lua"]},{"name":"Main","className":"Script","filePaths":["src/ServerScriptService\\Main.server.lua"]},{"name":"Tutorial","className":"Folder","filePaths":["src/ServerScriptService\\Tutorial\\init.meta.json"],"children":[{"name":"CenterPoint","className":"Script","filePaths":["src/ServerScriptService\\Tutorial\\CenterPoint.server.lua"]}]},{"name":"TycoonSentries","className":"Script","filePaths":["src/ServerScriptService\\TycoonSentries\\init.server.lua"],"children":[{"name":"TycoonSentry","className":"Script","filePaths":["src/ServerScriptService\\TycoonSentries\\TycoonSentry.server.lua"]}]}]},{"name":"ServerStorage","className":"ServerStorage","children":[{"name":"Modules","className":"Folder","filePaths":["src/ServerStorage/Modules\\init.meta.json"],"children":[{"name":"Casting","className":"ModuleScript","filePaths":["src/ServerStorage/Modules\\Casting\\init.lua"],"children":[{"name":"Scorer","className":"ModuleScript","filePaths":["src/ServerStorage/Modules\\Casting\\Scorer.lua"]}]},{"name":"OpenCloud","className":"Model","filePaths":["src/ServerStorage/Modules\\OpenCloud\\init.meta.json"],"children":[{"name":"V2","className":"ModuleScript","filePaths":["src/ServerStorage/Modules\\OpenCloud\\V2\\init.lua"],"children":[{"name":"UserNotification","className":"ModuleScript","filePaths":["src/ServerStorage/Modules\\OpenCloud\\V2\\UserNotification.lua"]}]}]}]}]},{"name":"StarterPlayer","className":"StarterPlayer","children":[{"name":"StarterCharacterScripts","className":"Folder","children":[{"name":"Main","className":"Script","filePaths":["src/StarterPlayer\\StarterCharacterScripts\\Main.client.lua"]}]}]}]}